{
  "table": "migrations",
  "schema": "storage",
  "database": "postgres_production",
  "description": "The storage.migrations table is a system metadata table that tracks database schema migration operations, storing each migration's unique identifier, descriptive name, content hash for integrity verification, and execution timestamp. Based on the sample data showing a \"create-migrations-table\" migration, this table serves as an audit log to ensure database schema changes are applied consistently and to prevent duplicate migration executions. The table operates independently without foreign key relationships, functioning as a standalone tracking mechanism for database version control and deployment processes.",
  "row_count": 0,
  "columns": [
    {
      "name": "id",
      "type": "integer",
      "nullable": false,
      "description": "Sequential numeric identifier that tracks the order and execution status of database schema changes. Based on the consecutive values starting from 0, this appears to represent migration scripts that have been applied to update the database structure.",
      "default": null
    },
    {
      "name": "name",
      "type": "character varying",
      "nullable": false,
      "description": "Records the descriptive identifier for each database migration operation, indicating the specific change or feature being implemented such as table creation, schema modifications, or security policy additions.",
      "default": null
    },
    {
      "name": "hash",
      "type": "character varying",
      "nullable": false,
      "description": "Contains unique cryptographic fingerprints that identify specific database schema changes or migration scripts. Each value represents a distinct version or state of the database structure modifications.",
      "default": null
    },
    {
      "name": "executed_at",
      "type": "timestamp without time zone",
      "nullable": true,
      "description": "Records the timestamp when a database migration was successfully executed. Based on the sample values showing identical timestamps, this likely captures when a batch of migrations were run together during a deployment or database update process.",
      "default": "CURRENT_TIMESTAMP"
    }
  ],
  "primary_key": [],
  "foreign_keys": [],
  "indexes": [
    {
      "index_name": "migrations_name_key",
      "index_definition": "CREATE UNIQUE INDEX migrations_name_key ON storage.migrations USING btree (name)",
      "columns": [
        "name"
      ],
      "is_unique": true
    },
    {
      "index_name": "migrations_pkey",
      "index_definition": "CREATE UNIQUE INDEX migrations_pkey ON storage.migrations USING btree (id)",
      "columns": [
        "id"
      ],
      "is_unique": true
    }
  ],
  "sample_data": [
    {
      "id": 0,
      "name": "create-migrations-table",
      "hash": "e18db593bcde2aca2a408c4d1100f6abba2195df",
      "executed_at": "2025-12-10T03:29:55.244Z"
    },
    {
      "id": 1,
      "name": "initialmigration",
      "hash": "6ab16121fbaa08bbd11b712d05f358f9b555d777",
      "executed_at": "2025-12-10T03:29:55.251Z"
    },
    {
      "id": 2,
      "name": "storage-schema",
      "hash": "5c7968fd083fcea04050c1b7f6253c9771b99011",
      "executed_at": "2025-12-10T03:29:55.257Z"
    },
    {
      "id": 3,
      "name": "pathtoken-column",
      "hash": "2cb1b0004b817b29d5b0a971af16bafeede4b70d",
      "executed_at": "2025-12-10T03:29:55.272Z"
    },
    {
      "id": 4,
      "name": "add-migrations-rls",
      "hash": "427c5b63fe1c5937495d9c635c263ee7a5905058",
      "executed_at": "2025-12-10T03:29:55.291Z"
    }
  ],
  "generated_at": "2025-12-11T22:51:15.516Z"
}